Lab 1/source.v
`timescale 1ns / 1ns

module lab1 (o,x,y,z);
    input x,y,z;
    output o;

    wire x_not, y_not, z_not;
    
    not(x_not,x);
    not(y_not,y);
    not(z_not,z);

    wire xy_not, x_noty, x_notyz_not;
    
    and(xy_not,x,y_not);
    and(x_noty,x_not,y);
    and(x_notyz_not,x_noty,z_not);

    or(o,x_notyz_not,xy_not);

endmodule //lab1

Lab 1/testbench.v
`timescale 1ns / 1ns

module lab1_1 ();

reg x,y,z;

wire o;

    lab1 lab(o,x,y,z);

initial begin
    $dumpfile("TimingDiagram.vcd");
	$dumpvars(0, o, x, y, z);

x = 0;  y = 0; z = 0; #20;
x = 0;  y = 0; z = 1; #20;
x = 0;  y = 1; z = 0; #20;
x = 0;  y = 1; z = 1; #20;
x = 1;  y = 0; z = 0; #20;
x = 1;  y = 0; z = 1; #20;
x = 1;  y = 1; z = 0; #20;
x = 1;  y = 1; z = 1; #20;
end

endmodule //lab1_1

Lab 1/TimingDiagram.vcd
$date
	Mon Apr 12 22:48:55 2021
$end
$version
	Icarus Verilog
$end
$timescale
	1ns
$end
$scope module lab1_1 $end
$var wire 1 ! o $end
$upscope $end
$scope module lab1_1 $end
$var reg 1 " x $end
$upscope $end
$scope module lab1_1 $end
$var reg 1 # y $end
$upscope $end
$scope module lab1_1 $end
$var reg 1 $ z $end
$upscope $end
$enddefinitions $end
#0
$dumpvars
0$
0#
0"
0!
$end
#20
1$
#40
1!
0$
1#
#60
0!
1$
#80
1!
0$
0#
1"
#100
1$
#120
0!
0$
1#
#140
1$
