Lab 2/source.v
`timescale 1ns/1ns

module mux(I1, I0, V0, V1, V2, V3, O);
    input I1, I0, V0, V1, V2, V3;
    output O;

    reg O;

    always @(I1, I0, V0, V1, V2, V3) 
    begin
        if (I1 == 0 && I0 == 0) begin
            O <= V0;
        end
        else
            if (I1 == 0 && I0  == 1) begin
            O <= V1;
            end
        else 
            if (I1 == 1 && I0 == 0) begin
            O <= V2;
            end
        else
            begin
            O <= V3;   
            end
    end
endmodule //source

module source (y, x0, x1, x2, x3);
    input x0, x1, x2, x3;
    output  y;

    wire w1, w4;

    and(w1, x0, x1);
    
    xor(w4, x0, x1);

    mux myMux(x3, x2, w1, x0, x1, w4, y);
endmodule //source

Lab 2/testbench.v
`timescale 1ns / 1ns

module testbench ();

reg x0, x1, x2, x3;

wire y;

    source lab(y, x0, x1, x2, x3);

    initial begin
        $dumpfile("TimingDiagram.vcd");
        $dumpvars(0, y, x0, x1, x2, x3);

        x3 = 0; x2 = 0; x1 = 0; x0 = 0; #20; 
        x3 = 0; x2 = 0; x1 = 0; x0 = 1; #20; 
        x3 = 0; x2 = 0; x1 = 1; x0 = 0; #20;
        x3 = 0; x2 = 0; x1 = 1; x0 = 1; #20;
        x3 = 0; x2 = 1; x1 = 0; x0 = 0; #20;
        x3 = 0; x2 = 1; x1 = 0; x0 = 1; #20;
        x3 = 0; x2 = 1; x1 = 1; x0 = 0; #20;
        x3 = 0; x2 = 1; x1 = 1; x0 = 1; #20;
        x3 = 1; x2 = 0; x1 = 0; x0 = 0; #20;
        x3 = 1; x2 = 0; x1 = 0; x0 = 1; #20;
        x3 = 1; x2 = 0; x1 = 1; x0 = 0; #20;
        x3 = 1; x2 = 0; x1 = 1; x0 = 1; #20;
        x3 = 1; x2 = 1; x1 = 0; x0 = 0; #20;
        x3 = 1; x2 = 1; x1 = 0; x0 = 1; #20;
        x3 = 1; x2 = 1; x1 = 1; x0 = 0; #20;
        x3 = 1; x2 = 1; x1 = 1; x0 = 1; #20;
        
    end

endmodule //testbench

Lab 2/TimingDiagram.vcd
$date
	Tue Apr 27 13:19:09 2021
$end
$version
	Icarus Verilog
$end
$timescale
	1ns
$end
$scope module testbench $end
$var wire 1 ! y $end
$upscope $end
$scope module testbench $end
$var reg 1 " x0 $end
$upscope $end
$scope module testbench $end
$var reg 1 # x1 $end
$upscope $end
$scope module testbench $end
$var reg 1 $ x2 $end
$upscope $end
$scope module testbench $end
$var reg 1 % x3 $end
$upscope $end
$enddefinitions $end
#0
$dumpvars
0%
0$
0#
0"
0!
$end
#20
1"
#40
0"
1#
#60
1!
1"
#80
0!
0"
0#
1$
#100
1!
1"
#120
0!
0"
1#
#140
1!
1"
#160
0!
0"
0#
0$
1%
#180
1"
#200
1!
0"
1#
#220
1"
#240
0!
0"
0#
1$
#260
1!
1"
#280
0"
1#
#300
0!
1"
